Metadata-Version: 2.1
Name: jjgimmethis
Version: 0.0.1
Summary: A module for generating random usernames, passwords, names and objects.
Home-page: https://github.com/jad-e/jjgimmethis
Author: Khoo Hui Ying
Author-email: khoohuiying01@gmail.com
License: MIT
Keywords: random,generator,username,password,name,objects
Platform: UNKNOWN
Classifier: Development Status :: 5 - Production/Stable
Classifier: Intended Audience :: Education
Classifier: Operating System :: Microsoft :: Windows :: Windows 10
Classifier: License :: OSI Approved :: MIT License
Classifier: Programming Language :: Python :: 3
License-File: LICENCE.txt
